_sass.pyd
pysassc.py
sass.py
sasstests.py
sassutils/__init__.py
sassutils/builder.py
sassutils/distutils.py
sassutils/wsgi.py
libsass_bin-0.23.0.dist-info/LICENSE
libsass_bin-0.23.0.dist-info/METADATA
libsass_bin-0.23.0.dist-info/WHEEL
libsass_bin-0.23.0.dist-info/entry_points.txt
libsass_bin-0.23.0.dist-info/top_level.txt
libsass_bin-0.23.0.dist-info/RECORD
